{
	"configurations" : 
	[
		{
			"directories" : 
			[
				{
					"build" : ".",
					"jsonFile" : "directory-.-Debug-d0094a50bb2071803777.json",
					"minimumCMakeVersion" : 
					{
						"string" : "3.26"
					},
					"projectIndex" : 0,
					"source" : ".",
					"targetIndexes" : 
					[
						0
					]
				}
			],
			"name" : "Debug",
			"projects" : 
			[
				{
					"directoryIndexes" : 
					[
						0
					],
					"name" : "problem_A_in_div2",
					"targetIndexes" : 
					[
						0
					]
				}
			],
			"targets" : 
			[
				{
					"directoryIndex" : 0,
					"id" : "problem_A_in_div2::@6890427a1f51a3e7e1df",
					"jsonFile" : "target-problem_A_in_div2-Debug-f4c85826c2c76d608585.json",
					"name" : "problem_A_in_div2",
					"projectIndex" : 0
				}
			]
		}
	],
	"kind" : "codemodel",
	"paths" : 
	{
		"build" : "C:/Users/tasnim/Desktop/problem solving/problem A in div2/cmake-build-debug",
		"source" : "C:/Users/tasnim/Desktop/problem solving/problem A in div2"
	},
	"version" : 
	{
		"major" : 2,
		"minor" : 5
	}
}
